kalabash_sievefilters/__init__.py
kalabash_sievefilters/apps.py
kalabash_sievefilters/constants.py
kalabash_sievefilters/forms.py
kalabash_sievefilters/handlers.py
kalabash_sievefilters/imaputils.py
kalabash_sievefilters/kbash_extension.py
kalabash_sievefilters/lib.py
kalabash_sievefilters/mocks.py
kalabash_sievefilters/rfc6266.py
kalabash_sievefilters/tests.py
kalabash_sievefilters/urls.py
kalabash_sievefilters/views.py
kalabash_sievefilters/locale/cs_CZ/LC_MESSAGES/django.mo
kalabash_sievefilters/locale/cs_CZ/LC_MESSAGES/django.po
kalabash_sievefilters/locale/cs_CZ/LC_MESSAGES/djangojs.mo
kalabash_sievefilters/locale/cs_CZ/LC_MESSAGES/djangojs.po
kalabash_sievefilters/locale/de/LC_MESSAGES/django.mo
kalabash_sievefilters/locale/de/LC_MESSAGES/django.po
kalabash_sievefilters/locale/de/LC_MESSAGES/djangojs.mo
kalabash_sievefilters/locale/de/LC_MESSAGES/djangojs.po
kalabash_sievefilters/locale/el_GR/LC_MESSAGES/django.mo
kalabash_sievefilters/locale/el_GR/LC_MESSAGES/django.po
kalabash_sievefilters/locale/el_GR/LC_MESSAGES/djangojs.mo
kalabash_sievefilters/locale/el_GR/LC_MESSAGES/djangojs.po
kalabash_sievefilters/locale/en/LC_MESSAGES/django.mo
kalabash_sievefilters/locale/en/LC_MESSAGES/django.po
kalabash_sievefilters/locale/en/LC_MESSAGES/djangojs.mo
kalabash_sievefilters/locale/en/LC_MESSAGES/djangojs.po
kalabash_sievefilters/locale/es/LC_MESSAGES/django.mo
kalabash_sievefilters/locale/es/LC_MESSAGES/django.po
kalabash_sievefilters/locale/es/LC_MESSAGES/djangojs.mo
kalabash_sievefilters/locale/es/LC_MESSAGES/djangojs.po
kalabash_sievefilters/locale/fr/LC_MESSAGES/django.mo
kalabash_sievefilters/locale/fr/LC_MESSAGES/django.po
kalabash_sievefilters/locale/fr/LC_MESSAGES/djangojs.mo
kalabash_sievefilters/locale/fr/LC_MESSAGES/djangojs.po
kalabash_sievefilters/locale/it/LC_MESSAGES/django.mo
kalabash_sievefilters/locale/it/LC_MESSAGES/django.po
kalabash_sievefilters/locale/it/LC_MESSAGES/djangojs.mo
kalabash_sievefilters/locale/it/LC_MESSAGES/djangojs.po
kalabash_sievefilters-1.6.2.dist-info/LICENSE
kalabash_sievefilters-1.6.2.dist-info/METADATA
kalabash_sievefilters-1.6.2.dist-info/WHEEL
kalabash_sievefilters-1.6.2.dist-info/top_level.txt
kalabash_sievefilters-1.6.2.dist-info/RECORD
